database_connector/__init__.py
database_connector/api.py
database_connector/database_connector.py
database_connector/merge_template.json
py_database_connector_Orinnass-2.4.7.dist-info/METADATA
py_database_connector_Orinnass-2.4.7.dist-info/WHEEL
py_database_connector_Orinnass-2.4.7.dist-info/top_level.txt
py_database_connector_Orinnass-2.4.7.dist-info/RECORD
