Metadata-Version: 2.1
Name: py-database-connector-Orinnass
Version: 2.4.7
Summary: UNKNOWN
Home-page: UNKNOWN
License: UNKNOWN
Download-URL: https://gitlab.com/Orinnass/python-module-database-connector
Platform: UNKNOWN
Requires-Python: >=3.10
Requires-Dist: Flask (>=2.0.2)
Requires-Dist: Jinja2 (>=3.0.3)
Requires-Dist: MarkupSafe (>=2.0.1)
Requires-Dist: PyMySQL (>=1.0.2)
Requires-Dist: Pygments (>=2.10.0)
Requires-Dist: SecretStorage (>=3.3.1)
Requires-Dist: Werkzeug (>=2.0.2)
Requires-Dist: attrs (>=21.2.0)
Requires-Dist: bleach (>=4.1.0)
Requires-Dist: certifi (>=2021.10.8)
Requires-Dist: cffi (>=1.15.0)
Requires-Dist: charset-normalizer (>=2.0.8)
Requires-Dist: click (>=8.0.3)
Requires-Dist: colorama (>=0.4.4)
Requires-Dist: coverage (>=6.2)
Requires-Dist: cryptography (>=36.0.0)
Requires-Dist: docutils (>=0.18.1)
Requires-Dist: idna (>=3.3)
Requires-Dist: importlib-metadata (>=4.8.2)
Requires-Dist: importlib-resources (>=5.4.0)
Requires-Dist: itsdangerous (>=2.0.1)
Requires-Dist: jeepney (>=0.7.1)
Requires-Dist: jsonschema (>=4.2.1)
Requires-Dist: keyring (>=23.4.0)
Requires-Dist: numpy (>=1.22.0rc1)
Requires-Dist: packaging (>=21.3)
Requires-Dist: pandas (>=1.3.4)
Requires-Dist: pkginfo (>=1.8.1)
Requires-Dist: py-configuration-Orinnass (>=2.3.9)
Requires-Dist: py-tools-Orinnass (>=2.0.10)
Requires-Dist: pycparser (>=2.21)
Requires-Dist: pymysql-pooling (>=1.0.6)
Requires-Dist: pyparsing (>=3.0.6)
Requires-Dist: pyrsistent (>=0.18.0)
Requires-Dist: python-dateutil (>=2.8.2)
Requires-Dist: pytz (>=2021.3)
Requires-Dist: pywin32-ctypes (>=0.2.0)
Requires-Dist: readme-renderer (>=30.0)
Requires-Dist: requests-toolbelt (>=0.9.1)
Requires-Dist: requests (>=2.26.0)
Requires-Dist: rfc3986 (>=1.5.0)
Requires-Dist: six (>=1.16.0)
Requires-Dist: tqdm (>=4.62.3)
Requires-Dist: twine (>=3.7.0)
Requires-Dist: urllib3 (>=1.26.7)
Requires-Dist: webencodings (>=0.5.1)
Requires-Dist: zipp (>=3.6.0)
